{"tasks":[{"id":"0b789a8d-8253-4793-b705-b3f80cde5dea","title":"csv parse","description":"test of csv parse","completed_at":null,"created_at":"20-08-2023","updated_at":"20-08-2023"},{"id":"6b033402-b1ab-499b-aa02-f968c65ba41d","title":"task 2 of test","description":"taske of test parse","completed_at":null,"created_at":"20-08-2023","updated_at":"20-08-2023"},{"id":"256ef5ad-28e2-4619-8cc4-65ef681059e8","title":"we are using the stream","description":"using the cvs parse ","completed_at":null,"created_at":"20-08-2023","updated_at":"20-08-2023"},{"id":"6080ded3-0587-4ee6-812c-7db80f180c47","title":"other task","description":"we can use this to import","completed_at":null,"created_at":"20-08-2023","updated_at":"20-08-2023"},{"id":"88379a9c-8a32-4bec-b35d-be3815396144","title":"task 5","description":"this is task 5","completed_at":null,"created_at":"20-08-2023","updated_at":"20-08-2023"},{"id":"7eebe438-2600-43c6-85d4-290c1fd0e552","title":"task 6","description":"this is task 6","completed_at":null,"created_at":"20-08-2023","updated_at":"20-08-2023"},{"id":"ab1b7282-5cfb-4fa0-b960-c6129fd291da","title":"task 7","description":"this is task 7","completed_at":null,"created_at":"20-08-2023","updated_at":"20-08-2023"},{"id":"952de671-c293-459e-977a-5d6221470227","title":"task 8","description":"this is task 8","completed_at":null,"created_at":"20-08-2023","updated_at":"20-08-2023"},{"id":"5829c414-2b13-4ba3-95a2-caa30b16e7fe","title":"task 9","description":"this is task 9","completed_at":null,"created_at":"20-08-2023","updated_at":"20-08-2023"},{"id":"41dce051-90cc-460f-9993-7fa465312bdc","title":"task 10","description":"this is task 10","completed_at":null,"created_at":"20-08-2023","updated_at":"20-08-2023"},{"id":"c3c5e5bd-7e8b-4cf9-9fc9-af5908e40c45","title":"task para testar 2","description":"mais uma para encher um pouco o DB 2","completed_at":null,"created_at":"20-08-2023","updated_at":"20-08-2023"}]}